hubblescope/__init__.py
hubblescope/__main__.py
hubblescope/datasets.py
hubblescope/fits.py
hubblescope/ingest.py
hubblescope/logger.py
hubblescope/urls.py
hubblescope/.abcli/abcli.sh
hubblescope/.abcli/actions.sh
hubblescope/.abcli/aka.sh
hubblescope/.abcli/download.sh
hubblescope/.abcli/get.sh
hubblescope/.abcli/hubble.sh
hubblescope/.abcli/install.sh
hubblescope/.abcli/list.sh
hubblescope/.abcli/select.sh
hubblescope/.abcli/tests/is_dataset.sh
hubblescope/.abcli/tests/list.sh
hubblescope/.abcli/tests/select_and_download.sh
hubblescope/.abcli/tests/version.sh
hubblescope-4.43.1.dist-info/LICENSE
hubblescope-4.43.1.dist-info/METADATA
hubblescope-4.43.1.dist-info/WHEEL
hubblescope-4.43.1.dist-info/top_level.txt
hubblescope-4.43.1.dist-info/RECORD
