Metadata-Version: 2.1
Name: hubblescope
Version: 4.43.1
Summary: 🔭 tools to access and process Hubble Space Telescope imagery and other datasets on AWS Open Data Registry.
Home-page: https://github.com/kamangir/hubble
Author: Arash Abadpour (Kamangir)
Author-email: arash@kamangir.net
License: Public Domain
Classifier: Programming Language :: Python :: 3
Classifier: Programming Language :: Unix Shell
Classifier: License :: Public Domain
Classifier: Operating System :: OS Independent
License-File: LICENSE
Requires-Dist: blueness
Requires-Dist: abcli
Requires-Dist: astropy[recommended]
Requires-Dist: boto3
Requires-Dist: geojson
Requires-Dist: geopandas
Requires-Dist: matplotlib
Requires-Dist: opencv-python
Requires-Dist: pymysql
Requires-Dist: pyyaml
Requires-Dist: pylint
Requires-Dist: pytest
Requires-Dist: python-dotenv[cli]
Requires-Dist: tqdm
